datagrok_celery_task/__init__.py
datagrok_celery_task/amqp_publisher.py
datagrok_celery_task/datagrok_task.py
datagrok_celery_task/func_call.py
datagrok_celery_task/logger.py
datagrok_celery_task/redirect.py
datagrok_celery_task/settings.py
datagrok_celery_task/utils.py
datagrok_celery_task-0.1.8.dist-info/METADATA
datagrok_celery_task-0.1.8.dist-info/WHEEL
datagrok_celery_task-0.1.8.dist-info/RECORD
