Metadata-Version: 2.4
Name: datagrok-celery-task
Version: 0.1.8
Summary: Celery Task wrapper to integrate Python functions into the Datagrok platform.
Project-URL: Homepage, https://github.com/datagrok-ai/public
Project-URL: Issues, https://github.com/datagrok-ai/public/issues
Author-email: Andrew Skalkin <askalkin@datagrok.ai>, Pavlo Polovyi <ppolovyi@datagrok.ai>, Alexander Paramonov <aparamonov@datagrok.ai>
Classifier: License :: OSI Approved :: MIT License
Classifier: Operating System :: OS Independent
Classifier: Programming Language :: Python :: 3
Classifier: Programming Language :: Python :: 3.8
Classifier: Programming Language :: Python :: 3.9
Requires-Python: >=3.8
Requires-Dist: celery>=5.5.2
Requires-Dist: pandas>=2.0.3
Requires-Dist: pyarrow>=17.0.0
Requires-Dist: websocket-client>=1.8.0
